haber_utils/__init__.py
haber_utils/utils.py
haber_utils-0.4.0.dist-info/LICENSE
haber_utils-0.4.0.dist-info/METADATA
haber_utils-0.4.0.dist-info/WHEEL
haber_utils-0.4.0.dist-info/top_level.txt
haber_utils-0.4.0.dist-info/RECORD
