Metadata-Version: 2.1
Name: haber-utils
Version: 0.4.0
Summary: General utility functions that keep being rewritten
Home-page: https://github.com/haberrj/utilities_library
Author: Ron Haber
Author-email: ron.haber@hotmail.com
License: MIT
Platform: UNKNOWN
Classifier: Programming Language :: Python :: 3
Classifier: License :: OSI Approved :: MIT License
Classifier: Operating System :: OS Independent
Requires-Python: >3.4
Requires-Dist: pandas
